CYuyanBianchengToushi/README.md
CYuyanBianchengToushi/__init__.py
CYuyanBianchengToushi/__main__.py
CYuyanBianchengToushi/file.epub
CYuyanBianchengToushi/index.html
CYuyanBianchengToushi/css/__init__.py
CYuyanBianchengToushi/css/annotations.css
CYuyanBianchengToushi/css/main.css
CYuyanBianchengToushi/css/normalize.css
CYuyanBianchengToushi/css/popup.css
CYuyanBianchengToushi/font/__init__.py
CYuyanBianchengToushi/font/fontello.eot
CYuyanBianchengToushi/font/fontello.svg
CYuyanBianchengToushi/font/fontello.ttf
CYuyanBianchengToushi/font/fontello.woff
CYuyanBianchengToushi/img/__init__.py
CYuyanBianchengToushi/img/annotator-glyph-sprite.png
CYuyanBianchengToushi/img/annotator-icon-sprite.png
CYuyanBianchengToushi/img/apple-touch-icon.png
CYuyanBianchengToushi/img/cancelfullscreen.png
CYuyanBianchengToushi/img/close.png
CYuyanBianchengToushi/img/fullscreen.png
CYuyanBianchengToushi/img/loader.gif
CYuyanBianchengToushi/img/menu-icon.png
CYuyanBianchengToushi/img/save.png
CYuyanBianchengToushi/img/saved.png
CYuyanBianchengToushi/img/settings-s.png
CYuyanBianchengToushi/img/settings.png
CYuyanBianchengToushi/img/star.png
CYuyanBianchengToushi/js/__init__.py
CYuyanBianchengToushi/js/epub.js
CYuyanBianchengToushi/js/epub.min.js
CYuyanBianchengToushi/js/epub.min.map
CYuyanBianchengToushi/js/hooks.min.js
CYuyanBianchengToushi/js/hooks.min.map
CYuyanBianchengToushi/js/reader.js
CYuyanBianchengToushi/js/reader.js.map
CYuyanBianchengToushi/js/reader.min.js
CYuyanBianchengToushi/js/reader.min.map
CYuyanBianchengToushi/js/hooks/__init__.py
CYuyanBianchengToushi/js/hooks/extensions/__init__.py
CYuyanBianchengToushi/js/hooks/extensions/highlight.js
CYuyanBianchengToushi/js/libs/__init__.py
CYuyanBianchengToushi/js/libs/jquery.min.js
CYuyanBianchengToushi/js/libs/localforage.min.js
CYuyanBianchengToushi/js/libs/screenfull.js
CYuyanBianchengToushi/js/libs/screenfull.min.js
CYuyanBianchengToushi/js/libs/zip.min.js
CYuyanBianchengToushi/js/plugins/__init__.py
c_yuyan_biancheng_toushi-2024.3.1.0.dist-info/METADATA
c_yuyan_biancheng_toushi-2024.3.1.0.dist-info/WHEEL
c_yuyan_biancheng_toushi-2024.3.1.0.dist-info/entry_points.txt
c_yuyan_biancheng_toushi-2024.3.1.0.dist-info/top_level.txt
c_yuyan_biancheng_toushi-2024.3.1.0.dist-info/RECORD
